{
    "k8s_resource": {
        "out": {
            "attributes": {
                "resource_name": {}
            }
        }
    },
    "aws_api_gateway": {
        "out": {
            "attributes": {
                "arn": {},
                "endpoint": {},
                "execution_arn": {},
                "id": {},
                "vpc_links_id": {},
                "stage_arn": {},
                "stage_execution_arn": {},
                "stage_id": {},
                "stage_invoke_url": {}
            }
        }
    },
    "cluster-autoscaler": {
        "out": {}
    },
    "prometheus_mysql_exporter": {
        "out": {}
    },
    "tcp_lb": {
        "out": {
            "interfaces": {
                "KEY": {
                    "host": {}
                }
            }
        }
    },
    "s3": {
        "out": {
            "attributes": {
                "bucket_name": {},
                "bucket_arn": {},
                "bucket_region": {},
                "read_only_iam_policy_arn": {},
                "read_write_iam_policy_arn": {}
            }
        }
    },
    "grafana_dashboard": {
        "out": {}
    },
    "schemahero_database": {
        "out": {}
    },
    "aws_waf": {
        "out": {
            "attributes": {
                "arn": {}
            }
        }
    },
    "alert_group": {
        "out": {}
    },
    "aws_dlm_lifecycle_policy": {},
    "aws_lambda_permission": {
        "out": {
            "attributes": {}
        }
    },
    "alb": {
        "out": {
            "interfaces": {
                "KEY": {
                    "username": {},
                    "password": {},
                    "host": {},
                    "port": {},
                    "name": {},
                    "connection_string": {}
                }
            }
        }
    },
    "azure_functions": {
        "out": {}
    },
    "google_cloud_storage": {
        "out": {
            "attributes": {
                "name": {},
                "url": {}
            }
        }
    },
    "helm": {},
    "mysql_user": {
        "out": {
            "attributes": {
                "username": {},
                "password": {}
            }
        }
    },
    "dynamodb": {
        "out": {
            "attributes": {
                "table_name": {},
                "table_arn": {},
                "read_only_policy": {},
                "read_write_policy": {}
            }
        }
    },
    "cloudflare": {
        "out": {}
    },
    "snapshot_schedule": {
        "out": {}
    },
    "iam_policy": {
        "out": {
            "attributes": {
                "name": {},
                "arn": {},
                "policy": {}
            }
        }
    },
    "aws_iam_role": {
        "out": {
            "attributes": {
                "irsa_iam_role_arn": {}
            }
        }
    },
    "prometheus_postgres_exporter": {
        "out": {}
    },
    "aws_event_bus": {
        "out": {}
    },
    "kubernetes_secret": {
        "out": {
            "attributes": {
                "name": {},
                "hash": {}
            }
        }
    },
    "loki_alerting_rules": {
        "out": {}
    },
    "service": {
        "out": {
            "interfaces": {
                "KEY": {
                    "host": {},
                    "port": {},
                    "username": {},
                    "password": {},
                    "connection_string": {},
                    "name": {}
                }
            },
            "attributes": {
                "service_name": {},
                "namespace": {},
                "resource_name": {},
                "resource_type": {},
                "selector_labels": {}
            }
        }
    },
    "vault": {
        "out": {
            "interfaces": {
                "server": {
                    "root_token": {},
                    "endpoint": {},
                    "port": {}
                }
            },
            "attributes": {
                "resource_name": {},
                "resource_type": {},
                "root_token": {},
                "secret_name": {}
            }
        }
    },
    "aws_efs": {
        "out": {
            "attributes": {
                "storage_class_name": {},
                "file_system_id": {}
            }
        }
    },
    "aws_lambda": {
        "out": {
            "attributes": {
                "function_name": {},
                "function_arn": {},
                "function_invoke_arn": {},
                "function_qualified_arn": {},
                "function_role_arn": {},
                "function_role_name": {}
            }
        }
    },
    "cloudfront": {
        "out": {
            "attributes": {
                "cloudfront_distribution_arn": {},
                "cloudfront_distribution_domain_name": {},
                "cloudfront_distribution_etag": {},
                "cloudfront_distribution_id": {},
                "cloudfront_distribution_last_modified_time": {}
            }
        }
    },
    "kafka": {
        "out": {
            "interfaces": {
                "cluster": {
                    "endpoint": {},
                    "username": {},
                    "password": {},
                    "connection_string": {}
                }
            }
        }
    },
    "gcp_iam_role": {
        "out": {
            "attributes": {
                "role_id": {}
            }
        }
    },
    "sqs": {
        "out": {
            "attributes": {
                "sqs_topic_name": {},
                "consumer_policy_arn": {},
                "producer_policy_arn": {},
                "queue_arn": {}
            }
        }
    },
    "artifactories": {
        "out": {
            "attributes": {
                "registry_secrets_list": {},
                "registry_secret_objects": {}
            }
        }
    },
    "log_collector": {
        "out": {}
    },
    "mysql": {
        "out": {
            "interfaces": {
                "reader": {
                    "username": {},
                    "password": {},
                    "host": {},
                    "port": {},
                    "connection_string": {}
                },
                "writer": {
                    "username": {},
                    "password": {},
                    "host": {},
                    "port": {},
                    "connection_string": {}
                }
            }
        }
    },
    "sns": {
        "out": {}
    },
    "status_check": {
        "out": {}
    },
    "loki_recording_rules": {
        "out": {}
    },
    "service_bus": {
        "out": {}
    },
    "dax_cluster": {
        "out": {}
    },
    "ingress": {
        "out": {
            "interfaces": {
                "KEY": {
                    "username": {},
                    "password": {},
                    "host": {},
                    "port": {},
                    "name": {},
                    "connection_string": {}
                }
            }
        }
    },
    "config_map": {
        "out": {
            "attributes": {
                "name": {},
                "hash": {}
            }
        }
    },
    "externaldns": {
        "out": {}
    },
    "peering": {
        "out": {
            "interfaces": {
                "username": {},
                "password": {},
                "host": {},
                "port": {},
                "name": {},
                "connection_string": {}
            }
        }
    },
    "aws_static_website": {
        "out": {
            "attributes": {}
        }
    },
    "aws_eventbridge": {
        "out": {}
    },
    "prometheus": {
        "out": {}
    },
    "schemahero": {
        "out": {}
    },
    "kubernetes_node_pool": {
        "out": {}
    },
    "elasticsearch": {
        "out": {
            "interfaces": {
                "cluster": {
                    "endpoint": {},
                    "connection_string": {}
                },
                "http": {
                    "host": {},
                    "port": {},
                    "connection_string": {}
                }
            }
        }
    },
    "kms": {
        "out": {
            "attributes": {
                "kms_key_arn": {},
                "kms_key_id": {},
                "kms_key_policy": {},
                "kms_external_key_expiration_model": {},
                "kms_external_key_state": {},
                "kms_external_key_usage": {},
                "kms_aliases": {},
                "kms_grants": {}
            }
        }
    },
    "postgres": {
        "out": {
            "interfaces": {
                "reader": {
                    "username": {},
                    "password": {},
                    "host": {},
                    "port": {},
                    "connection_string": {},
                    "db_names": {}
                },
                "writer": {
                    "username": {},
                    "password": {},
                    "host": {},
                    "port": {},
                    "connection_string": {},
                    "db_names": {}
                }
            }
        }
    },
    "container_service": {
        "out": {
            "attributes": {
                "cluster_arn": {},
                "cluster_name": {}
            }
        }
    },
    "cassandra": {
        "out": {}
    },
    "mongo": {
        "out": {
            "interfaces": {
                "cluster": {
                    "endpoint": {},
                    "username": {},
                    "password": {},
                    "connection_string": {}
                },
                "writer": {
                    "username": {},
                    "password": {},
                    "host": {},
                    "port": {},
                    "connection_string": {}
                },
                "reader": {
                    "username": {},
                    "password": {},
                    "host": {},
                    "port": {},
                    "connection_string": {}
                }
            }
        }
    },
    "pvc": {
        "out": {}
    },
    "atlas_account": {
        "out": {}
    },
    "mongo_user": {
        "out": {
            "attributes": {
                "username": {},
                "password": {}
            }
        }
    },
    "zookeeper": {
        "out": {
            "interfaces": {
                "KEY": {
                    "username": {},
                    "password": {},
                    "host": {},
                    "port": {},
                    "name": {},
                    "connection_string": {}
                }
            }
        }
    },
    "azure_storage_container": {
        "out": {
            "attributes": {
                "storage_account_name": {},
                "storage_account_id": {},
                "primary_access_key": {},
                "container_name": {}
            }
        }
    },
    "postgres_user": {
        "out": {
            "attributes": {
                "username": {},
                "password": {}
            }
        }
    },
    "rabbitmq": {
        "out": {
            "interfaces": {
                "cluster": {
                    "endpoint": {},
                    "username": {},
                    "password": {},
                    "connection_string": {}
                },
                "tcp": {
                    "host": {},
                    "port": {},
                    "username": {},
                    "password": {},
                    "connection_string": {}
                },
                "http": {
                    "host": {},
                    "port": {},
                    "username": {},
                    "password": {},
                    "connection_string": {}
                }
            }
        }
    },
    "redis": {
        "out": {
            "interfaces": {
                "reader": {
                    "username": {},
                    "password": {},
                    "host": {},
                    "port": {},
                    "connection_string": {}
                },
                "writer": {
                    "username": {},
                    "password": {},
                    "host": {},
                    "port": {},
                    "connection_string": {}
                }
            }
        }
    },
    "schemahero_table": {
        "out": {}
    },
    "kafka_topic": {
        "out": {}
    }
}